pyfmreader/__init__.py
pyfmreader/constants.py
pyfmreader/load_uff.py
pyfmreader/pyfmreader.py
pyfmreader/save_uff.py
pyfmreader/uff.py
pyfmreader/jpk/__init__.py
pyfmreader/jpk/loadjpkcurve.py
pyfmreader/jpk/loadjpkfile.py
pyfmreader/jpk/loadjpkimg.py
pyfmreader/jpk/loadjpkthermalfile.py
pyfmreader/jpk/parsejpkheader.py
pyfmreader/nanosc/__init__.py
pyfmreader/nanosc/loadnanosccurve.py
pyfmreader/nanosc/loadnanoscfile.py
pyfmreader/nanosc/loadnanoscimg.py
pyfmreader/nanosc/parsenanoscheader.py
pyfmreader/utils/__init__.py
pyfmreader/utils/forcecurve.py
pyfmreader/utils/segment.py
pyfmreader-0.1.3.dist-info/LICENSE.txt
pyfmreader-0.1.3.dist-info/METADATA
pyfmreader-0.1.3.dist-info/WHEEL
pyfmreader-0.1.3.dist-info/top_level.txt
pyfmreader-0.1.3.dist-info/RECORD
