Metadata-Version: 2.1
Name: pyfmreader
Version: 0.1.3
Summary: A python package to read Nanoscope and JPK AFM files.
Home-page: https://github.com/jlopezalo/PyFMReader
Author: Javier Lopez Alonso
Author-email: jla.lopez.18@gmail.com
Project-URL: Bug Tracker, https://github.com/jlopezalo/PyFMReader/issues
Project-URL: repository, https://github.com/jlopezalo/PyFMReader
Classifier: Programming Language :: Python :: 3
Classifier: License :: OSI Approved :: MIT License
Classifier: Operating System :: OS Independent
Requires-Python: >=3.6
License-File: LICENSE.txt
Requires-Dist: numpy
Requires-Dist: pandas
Requires-Dist: tifffile
